devocli/__init__.py
devocli/cdvs_mock.py
devocli/cfmmc.py
devocli/cmake.py
devocli/collect_videos.py
devocli/default.py
devocli/deploy_apk.py
devocli/dummy.py
devocli/find_big_files.py
devocli/fir.py
devocli/git.py
devocli/idea.py
devocli/java.py
devocli/lar.py
devocli/md5.py
devocli/misc.py
devocli/mobile.py
devocli/mobile_expo.py
devocli/mobile_ios.py
devocli/mysql.py
devocli/nginx.py
devocli/omni.py
devocli/omni_api_gmt.py
devocli/omni_diff_did_csv.py
devocli/omni_helper.py
devocli/omni_helper_app.py
devocli/omni_helper_ui.py
devocli/omni_postbuild.py
devocli/omni_server.py
devocli/pcsdk.py
devocli/remote.py
devocli/sample.py
devocli/sche.py
devocli/sync_imgs.py
devocli/tools.py
devocli/tools_expo.py
devocli/tools_java.py
devocli/tools_node.py
devocli/tools_scrapy.py
devocli/utf8bom.py
devocli/video.py
devocli/win.py
devocli/yyb.py
devolib/__init__.py
devolib/bot_feishu.py
devolib/consts.py
devolib/util_argparse.py
devolib/util_brew.py
devolib/util_cache.py
devolib/util_cmake.py
devolib/util_coll.py
devolib/util_crypt.py
devolib/util_dyip.py
devolib/util_env.py
devolib/util_exc.py
devolib/util_fs.py
devolib/util_httpc.py
devolib/util_java.py
devolib/util_js.py
devolib/util_json.py
devolib/util_log.py
devolib/util_orm.py
devolib/util_os.py
devolib/util_oss.py
devolib/util_prefer.py
devolib/util_py.py
devolib/util_str.py
devolib/util_tb.py
devolib/util_wxui.py
devolib/util_wxui_grid.py
devolib/util_wxui_options.py
devokay-0.8.31.dist-info/METADATA
devokay-0.8.31.dist-info/WHEEL
devokay-0.8.31.dist-info/entry_points.txt
devokay-0.8.31.dist-info/top_level.txt
devokay-0.8.31.dist-info/RECORD
