Metadata-Version: 2.4
Name: devokay
Version: 0.8.31
Summary: tools for daily developing.
Author-email: sevenli <asusual.cn@gmail.com>
License:                                  Apache License
Project-URL: text, https://github.com/devokay
Keywords: develop tools,git,nginx
Classifier: Intended Audience :: Developers
Classifier: Operating System :: OS Independent
Classifier: Programming Language :: Python :: 3
Requires-Python: >=3.6
Requires-Dist: requests
Requires-Dist: oss2
Requires-Dist: tabulate
Requires-Dist: cachetools
Requires-Dist: diskcache
Requires-Dist: paramiko
Requires-Dist: chardet
Requires-Dist: flask
Requires-Dist: pycryptodome
Requires-Dist: ply
Requires-Dist: openpyxl
